{
  "Aaron": [
    {
      "Action": "Firmly insists on seeing the correct body and challenges Brian about the mistake, showing concern for his father.",
      "Warmth": 1,
      "Chunk": 2
    },
    {
      "Action": "Uses humor and sarcasm ('This isn't Burger King. You can't just mess up my order.') to cope with the situation.",
      "Warmth": 1,
      "Chunk": 2
    },
    {
      "Action": "Threatens Brian jokingly ('or you're going to take his place'), indicating frustration but not genuine hostility.",
      "Warmth": 0,
      "Chunk": 2
    },
    {
      "Action": "Immediately recognizes that the body in the coffin is not his father and challenges Brian on the mistake.",
      "Competence": 1,
      "Chunk": 2
    },
    {
      "Action": "Expresses frustration clearly and demands accountability from Brian.",
      "Competence": 1,
      "Chunk": 2
    },
    {
      "Action": "Relies on Brian's assurance without taking further action himself to verify or resolve the situation.",
      "Competence": 0,
      "Chunk": 2
    },
    {
      "Action": "Admits to feeling overwhelmed and insecure about the funeral and his eulogy.",
      "Warmth": 1,
      "Chunk": 3
    },
    {
      "Action": "Acknowledges Michelle was right about the funeral arrangements and asks her not to rub it in.",
      "Warmth": 1,
      "Chunk": 3
    },
    {
      "Action": "Expresses frustration about family members not helping, especially Ryan.",
      "Warmth": 0,
      "Chunk": 3
    },
    {
      "Action": "Shares his worries openly with Michelle and allows her to comfort him.",
      "Warmth": 1,
      "Chunk": 3
    },
    {
      "Action": "Recognizes the mistake of using Marshals instead of a more reliable service and admits Michelle was right.",
      "Competence": 1,
      "Chunk": 3
    },
    {
      "Action": "Feels overwhelmed and doubts his ability to deliver a good eulogy, expressing low confidence.",
      "Competence": -1,
      "Chunk": 3
    },
    {
      "Action": "Attempts to prepare for the eulogy by reviewing index cards, showing some effort to fulfill his responsibilities.",
      "Competence": 1,
      "Chunk": 3
    },
    {
      "Action": "Complains about family members not helping and worries about others' perceptions, indicating distraction and stress.",
      "Competence": -1,
      "Chunk": 3
    },
    {
      "Action": "Assures Michelle he will take care of the down payment despite her frustration.",
      "Warmth": 1,
      "Chunk": 4
    },
    {
      "Action": "Looks away and seems uncomfortable when pressured about the eulogy and moving plans.",
      "Warmth": 0,
      "Chunk": 4
    },
    {
      "Action": "Pulls back when Michelle initiates intimacy at an inappropriate time, expressing concern about timing.",
      "Warmth": 1,
      "Chunk": 4
    },
    {
      "Action": "Assures Michelle he will take care of the condo down payment despite initial silence, showing a sense of responsibility.",
      "Competence": 1,
      "Chunk": 4
    },
    {
      "Action": "Looks away and avoids direct conversation about his writing and responsibilities, indicating discomfort and possible avoidance.",
      "Competence": -1,
      "Chunk": 4
    },
    {
      "Action": "Expresses reluctance and hesitation about intimacy at an inconvenient time, showing awareness of priorities but also some lack of decisiveness.",
      "Competence": 0,
      "Chunk": 4
    },
    {
      "Action": "Quickly stops intimate moment and responds appropriately when the housekeeper unexpectedly appears, showing awareness and discretion.",
      "Competence": 1,
      "Chunk": 7
    },
    {
      "Action": "Expresses hesitation and reluctance about having sex, asking if it must be done today, indicating some lack of confidence or decisiveness.",
      "Competence": -1,
      "Chunk": 7
    },
    {
      "Action": "Makes a sarcastic comment about Uncle Russell's personality, showing impatience.",
      "Warmth": -1,
      "Chunk": 8
    },
    {
      "Action": "Looks respectfully into the coffin and acknowledges his father.",
      "Warmth": 1,
      "Chunk": 8
    },
    {
      "Action": "Asks his mother how she is feeling, showing concern.",
      "Warmth": 1,
      "Chunk": 8
    },
    {
      "Action": "Lightly teases his mother about not liking Chinese food, attempting to lighten the mood.",
      "Warmth": 1,
      "Chunk": 8
    },
    {
      "Action": "Encourages his mother by telling her she is healthy and has friends and family, offering support.",
      "Warmth": 1,
      "Chunk": 8
    },
    {
      "Action": "Makes a witty, confident remark about Uncle Russell's personality, showing quick thinking and social awareness.",
      "Competence": 1,
      "Chunk": 8
    },
    {
      "Action": "Looks inside the coffin calmly and interacts respectfully with Brian, showing composure in a difficult situation.",
      "Competence": 1,
      "Chunk": 8
    },
    {
      "Action": "Comforts his mother Cynthia with encouraging words despite the emotional situation, demonstrating emotional intelligence and supportive behavior.",
      "Competence": 1,
      "Chunk": 8
    },
    {
      "Action": "Reassures Cynthia that Ryan will be here soon.",
      "Warmth": 1,
      "Chunk": 9
    },
    {
      "Action": "Turns away frustrated while looking at the coffin.",
      "Warmth": -1,
      "Chunk": 9
    },
    {
      "Action": "Reassures Cynthia that Ryan will be here soon, showing calmness and confidence in the situation.",
      "Competence": 1,
      "Chunk": 9
    },
    {
      "Action": "Turns away frustrated when looking at the coffin, indicating difficulty managing emotions or stress.",
      "Competence": -1,
      "Chunk": 9
    },
    {
      "Action": "No direct actions or statements by Aaron in this excerpt; only a brief mention of his younger brother Ryan's confident and successful demeanor.",
      "Competence": 0,
      "Chunk": 10
    },
    {
      "Action": "Makes a somewhat dark joke about seeing Ryan more often if people died every week.",
      "Warmth": 0,
      "Chunk": 11
    },
    {
      "Action": "Looks a bit lost in the background during family interaction, gives a somewhat awkward comment about death frequency.",
      "Competence": -1,
      "Chunk": 11
    },
    {
      "Action": "Responds calmly and briefly when asked how he is, showing some composure.",
      "Competence": 0,
      "Chunk": 11
    },
    {
      "Action": "Trails behind Ryan and stands over the coffin, showing some engagement with the situation.",
      "Warmth": 0,
      "Chunk": 12
    },
    {
      "Action": "Makes a sarcastic comment 'When does dead beat sick?'",
      "Warmth": -1,
      "Chunk": 12
    },
    {
      "Action": "Jokes about Ryan not calling, showing some familiarity and lightness.",
      "Warmth": 0,
      "Chunk": 12
    },
    {
      "Action": "Asks Ryan for money to pay for the funeral, insisting Ryan pay half.",
      "Warmth": -1,
      "Chunk": 12
    },
    {
      "Action": "Asks when dead beat sick, showing a lack of sensitivity and understanding of the situation.",
      "Competence": -1,
      "Chunk": 12
    },
    {
      "Action": "Reminds Ryan about needing money for the funeral and insists Ryan pay half, showing some assertiveness and practical thinking.",
      "Competence": 1,
      "Chunk": 12
    },
    {
      "Action": "Insists on splitting the cost despite Ryan not having the money, questions Ryan's spending choices.",
      "Warmth": -1,
      "Chunk": 13
    },
    {
      "Action": "Insists on splitting the cost despite Ryan's hesitation, firmly clarifies the arrangement.",
      "Competence": 1,
      "Chunk": 13
    },
    {
      "Action": "Questions Ryan about not having cash despite recent spending, showing awareness and attention to detail.",
      "Competence": 1,
      "Chunk": 13
    },
    {
      "Action": "No actions or statements by Aaron are present in the excerpt to evaluate competence.",
      "Competence": 0,
      "Chunk": 14
    },
    {
      "Action": "Greets mourners alongside Ryan.",
      "Warmth": 1,
      "Chunk": 16
    },
    {
      "Action": "Responds to Ryan's question about family members with uncertainty and a bit of sarcasm about paying for the funeral.",
      "Warmth": 0,
      "Chunk": 16
    },
    {
      "Action": "Greets mourners and attempts to manage the situation by waiting for everyone to arrive before starting the funeral.",
      "Competence": 1,
      "Chunk": 16
    },
    {
      "Action": "Does not recognize some family members and seems unsure about who certain people are.",
      "Competence": -1,
      "Chunk": 16
    },
    {
      "Action": "Expresses frustration about having to pay for the funeral and refuses to act as a credit agency.",
      "Competence": 0,
      "Chunk": 16
    },
    {
      "Action": "Introduces his brother Ryan to Reverend Davis.",
      "Warmth": 1,
      "Chunk": 17
    },
    {
      "Action": "Insists on doing the eulogy despite others' expectations.",
      "Warmth": 0,
      "Chunk": 17
    },
    {
      "Action": "Acknowledges that many attendees are there to hear Ryan's eulogy, showing awareness of others' feelings.",
      "Warmth": 1,
      "Chunk": 17
    },
    {
      "Action": "Insists on doing the eulogy despite others' expectations and tries to assert his role as the oldest sibling.",
      "Competence": 0,
      "Chunk": 17
    },
    {
      "Action": "Appears irritated and somewhat insecure when the reverend shows more interest in Ryan, indicating a lack of confidence.",
      "Competence": -1,
      "Chunk": 17
    },
    {
      "Action": "Finds a quiet place to prepare a speech about his father, showing respect and sincerity.",
      "Warmth": 1,
      "Chunk": 18
    },
    {
      "Action": "Responds to Michelle's attempt to help with reluctance and dismissiveness, indicating emotional distance.",
      "Warmth": -1,
      "Chunk": 18
    },
    {
      "Action": "Finds a quiet place in the hallway and pulls out his notes to prepare a speech for the funeral.",
      "Competence": 1,
      "Chunk": 18
    },
    {
      "Action": "Repeats the same line over and over while practicing, indicating difficulty in preparing the speech.",
      "Competence": 0,
      "Chunk": 18
    },
    {
      "Action": "Avoids discussing the speech with Michelle, showing reluctance and lack of focus.",
      "Competence": -1,
      "Chunk": 18
    },
    {
      "Action": "Responds to Michelle's inappropriate comment with confusion and distraction, showing lack of emotional control and focus.",
      "Competence": -1,
      "Chunk": 18
    },
    {
      "Action": "Tries to discreetly warn Michelle about the man staring at him, showing concern and caution.",
      "Warmth": 1,
      "Chunk": 19
    },
    {
      "Action": "Avoids direct confrontation by averting his eyes when making eye contact with the man.",
      "Warmth": 0,
      "Chunk": 19
    },
    {
      "Action": "Tries to discreetly alert Michelle about the suspicious man without causing a scene.",
      "Competence": 1,
      "Chunk": 19
    },
    {
      "Action": "Appears nervous and avoids direct confrontation or investigation with the man staring at him.",
      "Competence": 0,
      "Chunk": 19
    },
    {
      "Action": "Attempts to delegate watching out to Ryan but is interrupted and distracted.",
      "Competence": 0,
      "Chunk": 19
    },
    {
      "Action": "Looks distastefully at his brother.",
      "Warmth": -1,
      "Chunk": 20
    },
    {
      "Action": "Asks Ryan to keep an eye out for Uncle Russell.",
      "Warmth": 1,
      "Chunk": 20
    },
    {
      "Action": "Responds uncomfortably but politely to Frank's condolences and shakes his hand.",
      "Warmth": 1,
      "Chunk": 20
    },
    {
      "Action": "Walks away leaving Frank alone after a brief interaction.",
      "Warmth": 0,
      "Chunk": 20
    },
    {
      "Action": "Requests to wait for Uncle Russell before starting the service.",
      "Warmth": 1,
      "Chunk": 20
    },
    {
      "Action": "Delegates the task of checking on Martina to Ryan, showing some situational awareness and trust.",
      "Competence": 1,
      "Chunk": 20
    },
    {
      "Action": "Politely handles an uncomfortable social interaction with Frank, maintaining composure.",
      "Competence": 1,
      "Chunk": 20
    },
    {
      "Action": "Leaves Frank alone after a brief exchange without probing further, possibly missing an opportunity to gather information.",
      "Competence": -1,
      "Chunk": 20
    },
    {
      "Action": "Requests a delay to start the funeral until Uncle Russell arrives, showing some organizational awareness.",
      "Competence": 1,
      "Chunk": 20
    },
    {
      "Action": "Answers Duncan's question about timing clearly and confidently.",
      "Competence": 1,
      "Chunk": 21
    },
    {
      "Action": "Responds briefly and walks away when Duncan questions him about the eulogy situation, showing some discomfort or avoidance.",
      "Competence": 0,
      "Chunk": 21
    },
    {
      "Action": "Expresses frustration about family dynamics and feeling overlooked for the eulogy despite being the oldest and caretaker.",
      "Warmth": 1,
      "Chunk": 22
    },
    {
      "Action": "Welcomes a man looking for soda into the garage with a friendly 'Yes! Come in!'",
      "Warmth": 1,
      "Chunk": 22
    },
    {
      "Action": "Stops intimate moment with Michelle to lean on the door and sigh, showing vulnerability and stress.",
      "Warmth": 1,
      "Chunk": 22
    },
    {
      "Action": "Expresses frustration about having to do the eulogy but acknowledges responsibility as the oldest son.",
      "Competence": 0,
      "Chunk": 22
    },
    {
      "Action": "Responds promptly and positively to a knock on the door, inviting the person in.",
      "Competence": 1,
      "Chunk": 22
    },
    {
      "Action": "Thanks Derek sincerely for helping with the wheelchair and calls him a life saver.",
      "Warmth": 1,
      "Chunk": 25
    },
    {
      "Action": "Wheels Uncle Russell inside and asks how he is doing.",
      "Warmth": 1,
      "Chunk": 25
    },
    {
      "Action": "Asks to postpone a conversation with Frank because his uncle just arrived.",
      "Warmth": 0,
      "Chunk": 25
    },
    {
      "Action": "Straightens his tie and practices his eulogy, showing preparation and focus.",
      "Competence": 1,
      "Chunk": 25
    },
    {
      "Action": "Politely defers Frank's request to talk until later, managing social timing well.",
      "Competence": 1,
      "Chunk": 25
    },
    {
      "Action": "Thanks Derek and wheels Uncle Russell inside, showing responsibility and helpfulness.",
      "Competence": 1,
      "Chunk": 25
    },
    {
      "Action": "Wheels Uncle Russell to his place despite the uncle's grumpiness.",
      "Warmth": 1,
      "Chunk": 26
    },
    {
      "Action": "Nods politely to Reverend Davis upon entering.",
      "Warmth": 1,
      "Chunk": 26
    },
    {
      "Action": "Takes his seat quietly with Michelle without causing disturbance.",
      "Warmth": 0,
      "Chunk": 26
    },
    {
      "Action": "Wheels Uncle Russell to his place despite Russell's grumpiness and poking others with his cane.",
      "Competence": 1,
      "Chunk": 26
    },
    {
      "Action": "Enters and nods to Reverend Davis calmly, then takes his seat with Michelle without causing disruption.",
      "Competence": 1,
      "Chunk": 26
    },
    {
      "Action": "Interrupts Norman and Elaine's whispering to reprimand them for inappropriate behavior during the funeral, reminding them to act respectfully because his father is dead.",
      "Warmth": 1,
      "Chunk": 27
    },
    {
      "Action": "Interrupts the whispering by loudly asking 'What the hell is going on?!' to restore order and remind others of the solemnity of the occasion.",
      "Competence": 1,
      "Chunk": 27
    },
    {
      "Action": "Whispers to Norman to remind him that his father is dead and to act appropriately, showing awareness of social context and emotional intelligence.",
      "Competence": 1,
      "Chunk": 27
    },
    {
      "Action": "Looks worried during the service, indicating emotional involvement but no clear action to manage the situation.",
      "Competence": 0,
      "Chunk": 27
    },
    {
      "Action": "Gathers himself nervously to give a eulogy at his father's funeral, showing vulnerability and sincerity.",
      "Warmth": 1,
      "Chunk": 28
    },
    {
      "Action": "Makes a self-deprecating comment about his father having more friends now that he's dead, showing honesty but awkwardness.",
      "Warmth": 1,
      "Chunk": 28
    },
    {
      "Action": "Continues speaking calmly despite Oscar's disruptive laughter and pain, showing tolerance and composure.",
      "Warmth": 1,
      "Chunk": 28
    },
    {
      "Action": "Gathers himself despite extreme nervousness and begins the eulogy, attempting to speak publicly.",
      "Competence": 0,
      "Chunk": 28
    },
    {
      "Action": "Voice cracks and eulogy content is awkward and poorly received, causing discomfort and concern among listeners.",
      "Competence": -1,
      "Chunk": 28
    },
    {
      "Action": "Composes himself after initial stumble and continues speaking, showing some resilience.",
      "Competence": 1,
      "Chunk": 28
    },
    {
      "Action": "Continues delivering the eulogy calmly despite Oscar's disruptive behavior.",
      "Warmth": 0,
      "Chunk": 29
    },
    {
      "Action": "Looks over to Oscar when he becomes agitated, showing some awareness and concern.",
      "Warmth": 1,
      "Chunk": 29
    },
    {
      "Action": "Continues delivering the eulogy despite clear disturbances and warnings from others.",
      "Competence": -1,
      "Chunk": 29
    },
    {
      "Action": "Stops the eulogy when Oscar jumps up and causes a scene.",
      "Competence": 1,
      "Chunk": 29
    },
    {
      "Action": "Tries to restrain Oscar to prevent chaos at the funeral.",
      "Warmth": 1,
      "Chunk": 30
    },
    {
      "Action": "Freezes in shock when the coffin tips over and the body falls out.",
      "Warmth": 0,
      "Chunk": 30
    },
    {
      "Action": "Is angry and marches out instead of comforting Cynthia who is crying.",
      "Warmth": -1,
      "Chunk": 30
    },
    {
      "Action": "Tries to restrain Oscar and Elaine from opening the coffin, attempts to maintain order during chaos.",
      "Competence": 1,
      "Chunk": 30
    },
    {
      "Action": "Freezes in shock when the coffin tips over and the body falls out.",
      "Competence": -1,
      "Chunk": 30
    },
    {
      "Action": "Shows anger and frustration by marching out instead of helping to calm the situation.",
      "Competence": -1,
      "Chunk": 30
    },
    {
      "Action": "Storms out to confront Elaine about the disturbing situation, showing concern for his dead father and family.",
      "Warmth": 1,
      "Chunk": 31
    },
    {
      "Action": "Dismisses Michelle abruptly and refuses to engage with her, misunderstanding her intentions.",
      "Warmth": -1,
      "Chunk": 31
    },
    {
      "Action": "Storms out to confront Elaine about the disturbing situation, showing initiative and concern.",
      "Competence": 1,
      "Chunk": 31
    },
    {
      "Action": "Turns away annoyed and confused when told to go back inside without explanation, showing some lack of patience or understanding.",
      "Competence": 0,
      "Chunk": 31
    },
    {
      "Action": "Refuses to engage in a misunderstanding with Michelle and directly asks what she was going to say, demonstrating clear communication and control.",
      "Competence": 1,
      "Chunk": 31
    },
    {
      "Action": "Gently asks Norman to stop interrupting, shows patience.",
      "Warmth": 1,
      "Chunk": 33
    },
    {
      "Action": "Suggests Norman show his wrist issue to Uncle Duncan, a doctor, to help him.",
      "Warmth": 1,
      "Chunk": 33
    },
    {
      "Action": "Suggests Norman show his wrist issue to Uncle Duncan, a doctor, demonstrating practical thinking and directing to an appropriate resource.",
      "Competence": 1,
      "Chunk": 33
    },
    {
      "Action": "No actions or statements present in the excerpt to evaluate competence.",
      "Competence": 0,
      "Chunk": 35
    },
    {
      "Action": "Reassures a concerned mourner by saying 'It's alright.'",
      "Warmth": 1,
      "Chunk": 37
    },
    {
      "Action": "Turns around not knowing what to do after trying to comfort mourner.",
      "Warmth": 0,
      "Chunk": 37
    },
    {
      "Action": "Agrees to talk privately with Frank and walks away with him.",
      "Warmth": 0,
      "Chunk": 37
    },
    {
      "Action": "Approaches a concerned mourner and tries to reassure them by saying 'It's alright.'",
      "Competence": 0,
      "Chunk": 37
    },
    {
      "Action": "Turns around not knowing what to do after trying to reassure mourner.",
      "Competence": -1,
      "Chunk": 37
    },
    {
      "Action": "Agrees to go somewhere private with Frank to talk.",
      "Competence": 0,
      "Chunk": 37
    },
    {
      "Action": "Walks to the desk and handles the manuscript with his name on it when entering the study.",
      "Competence": 0,
      "Chunk": 37
    },
    {
      "Action": "Responds hesitantly to Frank's question about writing a novel and moves the manuscript away.",
      "Competence": -1,
      "Chunk": 37
    },
    {
      "Action": "Motions for Frank to take a seat and sits across from him, engaging in conversation.",
      "Warmth": 1,
      "Chunk": 38
    },
    {
      "Action": "Moves the conversation on when Frank praises his brother, avoiding potential awkwardness.",
      "Warmth": 0,
      "Chunk": 38
    },
    {
      "Action": "Looks at photos curiously but becomes more suspicious as Frank shows more.",
      "Warmth": 0,
      "Chunk": 38
    },
    {
      "Action": "Corrects Frank confidently about being the oldest sibling and having published work in the New Yorker.",
      "Competence": 1,
      "Chunk": 38
    },
    {
      "Action": "Attempts to steer the conversation away from Frank's praise of his brother, showing social awareness and control.",
      "Competence": 1,
      "Chunk": 38
    },
    {
      "Action": "Responds to Frank's vague statements about his father with short, non-committal answers, possibly indicating discomfort or lack of engagement.",
      "Competence": 0,
      "Chunk": 38
    },
    {
      "Action": "Becomes suspicious when shown photos by Frank, indicating alertness and critical thinking.",
      "Competence": 1,
      "Chunk": 38
    },
    {
      "Action": "Expresses shock and disgust upon learning a hidden truth about his father, then quickly gathers himself to ask practical questions.",
      "Warmth": 0,
      "Chunk": 39
    },
    {
      "Action": "Closes the study door after the revelation, indicating a desire for privacy or to process emotions alone.",
      "Warmth": 0,
      "Chunk": 39
    },
    {
      "Action": "Looks carefully at the photos and surroundings, gradually putting together the clues to understand Frank's relationship with his father.",
      "Competence": 1,
      "Chunk": 39
    },
    {
      "Action": "Jumps up and closes the study door abruptly after realizing the truth, showing emotional reaction but also a desire for privacy.",
      "Competence": 0,
      "Chunk": 39
    },
    {
      "Action": "Asks Frank if his mother knows about the situation, indicating he is trying to gather important information.",
      "Competence": 1,
      "Chunk": 39
    },
    {
      "Action": "Shakes in disgust and expresses shock, showing emotional overwhelm but not necessarily a lack of competence.",
      "Competence": 0,
      "Chunk": 39
    },
    {
      "Action": "Fails to respond initially, then gets angry and physically pushes Frank when confronted with accusations and demands.",
      "Warmth": -1,
      "Chunk": 40
    },
    {
      "Action": "Refuses to give Frank money despite his demands, citing personal financial concerns and family plans.",
      "Warmth": 0,
      "Chunk": 40
    },
    {
      "Action": "Snatches a photo from Frank to prevent further manipulation and tries to control the situation.",
      "Warmth": 0,
      "Chunk": 40
    },
    {
      "Action": "Stares silently and moves away when approached by old acquaintances reminiscing about his father.",
      "Warmth": -1,
      "Chunk": 41
    },
    {
      "Action": "Looks pale and anxious while mingling at the funeral, searching for Ryan.",
      "Warmth": 0,
      "Chunk": 41
    },
    {
      "Action": "Stares silently at the men reminiscing about his father, then moves toward the living room without engaging or responding.",
      "Competence": 0,
      "Chunk": 41
    },
    {
      "Action": "Goes pale and mutters 'Oh God, oh God, oh God...' to himself while looking for Ryan but fails to find him.",
      "Competence": -1,
      "Chunk": 41
    },
    {
      "Action": "Insists on talking to Ryan about an important matter despite initial resistance.",
      "Warmth": 1,
      "Chunk": 42
    },
    {
      "Action": "Shares sensitive information about their father’s secret relationship.",
      "Warmth": 1,
      "Chunk": 42
    },
    {
      "Action": "Insists on talking to Ryan despite initial dismissal, pulls him aside to discuss an important matter privately.",
      "Competence": 1,
      "Chunk": 42
    },
    {
      "Action": "Shares critical information about the mysterious man and his connection to their father, showing awareness and initiative.",
      "Competence": 1,
      "Chunk": 42
    },
    {
      "Action": "Uses evidence (pictures) to support his claim, demonstrating preparation and thoughtfulness.",
      "Competence": 1,
      "Chunk": 42
    },
    {
      "Action": "Persists in conveying difficult truth despite Ryan's denial and resistance.",
      "Competence": 1,
      "Chunk": 42
    },
    {
      "Action": "Insists on paying the blackmailer to protect his mother, showing responsibility and concern for family.",
      "Warmth": 1,
      "Chunk": 45
    },
    {
      "Action": "Argues with Ryan about money and financial responsibility, showing frustration but also a sense of fairness.",
      "Warmth": 0,
      "Chunk": 45
    },
    {
      "Action": "Argues logically about financial responsibilities and challenges Ryan's suggestion to pay the money without a plan.",
      "Competence": 1,
      "Chunk": 45
    },
    {
      "Action": "Shows the incriminating photo to Ryan to emphasize the seriousness of the threat.",
      "Competence": 1,
      "Chunk": 45
    },
    {
      "Action": "Expresses frustration but does not propose a clear solution to the extortion problem.",
      "Competence": 0,
      "Chunk": 45
    },
    {
      "Action": "Politely asks Reverend Davis for five more minutes before starting the service.",
      "Warmth": 1,
      "Chunk": 46
    },
    {
      "Action": "Gently tells Michelle that buying a condo has to be put on hold, apologizing and trying to explain.",
      "Warmth": 1,
      "Chunk": 46
    },
    {
      "Action": "Refuses to explain the reason to Michelle immediately, asking her to give him time.",
      "Warmth": 0,
      "Chunk": 46
    },
    {
      "Action": "Asks the reverend for five more minutes before starting the service, showing awareness of timing and authority.",
      "Competence": 1,
      "Chunk": 46
    },
    {
      "Action": "Calmly informs Michelle that buying a condo must be put on hold, indicating clear communication and prioritization.",
      "Competence": 1,
      "Chunk": 46
    },
    {
      "Action": "Refuses to explain the reason for postponing the condo purchase, potentially showing avoidance or withholding information.",
      "Competence": 0,
      "Chunk": 46
    },
    {
      "Action": "Rushes over and takes manuscript away from Frank, protecting his work.",
      "Warmth": 1,
      "Chunk": 47
    },
    {
      "Action": "Irritated but tries to negotiate a deal to protect his mother and family privacy.",
      "Warmth": 1,
      "Chunk": 47
    },
    {
      "Action": "Reluctantly writes a check to Frank to keep peace and protect family.",
      "Warmth": 1,
      "Chunk": 47
    },
    {
      "Action": "Rushes over and takes the manuscript away from Frank, asserting control over his work.",
      "Competence": 1,
      "Chunk": 47
    },
    {
      "Action": "Negotiates a deal with Frank to get photos and keep him away from their mother, showing practical problem-solving.",
      "Competence": 1,
      "Chunk": 47
    },
    {
      "Action": "Reluctantly writes a check to settle the issue, demonstrating willingness to take responsibility and act decisively.",
      "Competence": 1,
      "Chunk": 47
    },
    {
      "Action": "Initially dismisses Frank's comment about the manuscript being a first draft without much reflection.",
      "Competence": 0,
      "Chunk": 47
    },
    {
      "Action": "Rips the check into little pieces, refuses to give money to someone he distrusts on the day of his father's funeral.",
      "Warmth": -1,
      "Chunk": 48
    },
    {
      "Action": "Expresses frustration and prioritizes his own feelings over others' requests during a sensitive moment.",
      "Warmth": -1,
      "Chunk": 48
    },
    {
      "Action": "Rips the check into little pieces, refuses to give money despite the situation, shows strong emotional reaction but no clear plan or solution.",
      "Competence": -1,
      "Chunk": 48
    },
    {
      "Action": "Expresses frustration clearly and decisively, attempts to end the conflict quickly by saying 'Let's just get it over with.'",
      "Competence": 0,
      "Chunk": 48
    },
    {
      "Action": "Stands between Ryan and Frank to stop their fight, showing concern.",
      "Warmth": 1,
      "Chunk": 49
    },
    {
      "Action": "Helps Ryan by grabbing curtain cord and tying Frank's legs despite discomfort.",
      "Warmth": 1,
      "Chunk": 49
    },
    {
      "Action": "Expresses reluctance and discomfort about restraining Frank, indicating moral hesitation.",
      "Warmth": 1,
      "Chunk": 49
    },
    {
      "Action": "Watches the fight shocked and initially hesitates to intervene.",
      "Competence": -1,
      "Chunk": 49
    },
    {
      "Action": "Responds to Ryan's request by quickly grabbing the curtain cord to restrain Frank.",
      "Competence": 1,
      "Chunk": 49
    },
    {
      "Action": "Expresses doubt about the plan, indicating awareness of the risks.",
      "Competence": 1,
      "Chunk": 49
    },
    {
      "Action": "Falls on top of Frank while trying to tie his legs, showing clumsiness in a tense situation.",
      "Competence": -1,
      "Chunk": 49
    },
    {
      "Action": "Avoids Michelle and is distant during a difficult time.",
      "Warmth": -1,
      "Chunk": 50
    },
    {
      "Action": "Struggles with Ryan to restrain Frank, showing willingness to help despite discomfort.",
      "Warmth": 1,
      "Chunk": 50
    },
    {
      "Action": "Struggles to understand how to use a tie to gag Frank, asks for clarification, and shows hesitation.",
      "Competence": -1,
      "Chunk": 50
    },
    {
      "Action": "Grabs the necktie promptly when asked, attempts to follow Ryan's instructions despite uncertainty.",
      "Competence": 0,
      "Chunk": 50
    },
    {
      "Action": "Holds Frank's nose closed to administer Valium despite Frank's protests, helping to calm him during a seizure.",
      "Warmth": 1,
      "Chunk": 51
    },
    {
      "Action": "Engages in secretive behavior about blackmail, refusing to explain to others.",
      "Warmth": -1,
      "Chunk": 51
    },
    {
      "Action": "Shows uncertainty and lack of clear plan about what to do with Frank.",
      "Warmth": 0,
      "Chunk": 51
    },
    {
      "Action": "Holds Frank's nose closed to help administer Valium during a seizure.",
      "Competence": 1,
      "Chunk": 51
    },
    {
      "Action": "Engages in discussion about what to do with Frank but shows no clear plan or solution.",
      "Competence": -1,
      "Chunk": 51
    },
    {
      "Action": "Expresses concern about how long they can keep Frank tied up and urges Ryan to come up with a solution so they can all live happily ever after.",
      "Warmth": 1,
      "Chunk": 52
    },
    {
      "Action": "Sarcastically questions Jeff about the source of the drugs with a mocking comment ('What friend, Amy Winehouse?').",
      "Warmth": -1,
      "Chunk": 52
    },
    {
      "Action": "Questions Norman about how many pills he gave to Frank, showing some concern about the situation.",
      "Warmth": 0,
      "Chunk": 52
    },
    {
      "Action": "Suggests calling an ambulance for Frank who is in distress.",
      "Warmth": 1,
      "Chunk": 53
    },
    {
      "Action": "Tries to appear normal and calm when Cynthia knocks on the door, responding politely.",
      "Warmth": 1,
      "Chunk": 53
    },
    {
      "Action": "Suggests calling an ambulance when Frank is in distress.",
      "Competence": 1,
      "Chunk": 53
    },
    {
      "Action": "Questions what will happen if they don't call for help, showing concern and seeking clarity.",
      "Competence": 1,
      "Chunk": 53
    },
    {
      "Action": "Responds calmly and normally to Cynthia knocking on the door, attempting to maintain composure.",
      "Competence": 1,
      "Chunk": 53
    },
    {
      "Action": "Passively follows Ryan's plan to leave Norman and Jeff to watch Frank without proposing alternatives or solutions.",
      "Competence": 0,
      "Chunk": 53
    },
    {
      "Action": "Apologizes to Reverend Davis and asks for more time politely.",
      "Warmth": 1,
      "Chunk": 54
    },
    {
      "Action": "Argues with Ryan about the consequences of tying up the reverend, showing concern about their mother's reaction.",
      "Warmth": 1,
      "Chunk": 54
    },
    {
      "Action": "Asks the reverend politely for five more minutes to resume service, attempting to manage the situation calmly.",
      "Competence": 1,
      "Chunk": 54
    },
    {
      "Action": "Engages in a heated argument with Ryan about the tied-up man instead of resolving the issue quickly.",
      "Competence": -1,
      "Chunk": 54
    },
    {
      "Action": "Argues with Ryan about who tied someone up, showing engagement in the situation but no clear resolution or leadership.",
      "Competence": 0,
      "Chunk": 56
    },
    {
      "Action": "Insists he has been looking out for Mom, showing a sense of responsibility.",
      "Warmth": 1,
      "Chunk": 57
    },
    {
      "Action": "Engages in a bitter argument with Ryan, trading insults and jealousy.",
      "Warmth": -1,
      "Chunk": 57
    },
    {
      "Action": "Dismisses Michelle's attempt to connect and be intimate, asking her to wait.",
      "Warmth": -1,
      "Chunk": 57
    },
    {
      "Action": "Shares a difficult and sensitive truth with Michelle about his father, showing honesty and trust.",
      "Warmth": 1,
      "Chunk": 57
    },
    {
      "Action": "Engages in a heated argument with Ryan, showing emotional intensity but no clear resolution or control.",
      "Competence": 0,
      "Chunk": 57
    },
    {
      "Action": "Has spent three years working on a novel, demonstrating persistence and dedication to a complex task.",
      "Competence": 1,
      "Chunk": 57
    },
    {
      "Action": "Refuses to share his novel with others, possibly indicating insecurity or lack of confidence in his work.",
      "Competence": -1,
      "Chunk": 57
    },
    {
      "Action": "Closes the garage door to have a private conversation with Michelle, showing awareness of the need for discretion.",
      "Competence": 1,
      "Chunk": 57
    },
    {
      "Action": "Reveals a shocking and sensitive family secret to Michelle, indicating willingness to confront difficult truths but possibly lacking tact.",
      "Competence": 0,
      "Chunk": 57
    },
    {
      "Action": "Shows Michelle the incriminating picture confidently to reveal the blackmail threat.",
      "Competence": 1,
      "Chunk": 58
    },
    {
      "Action": "No actions or statements by Aaron in the excerpt to evaluate competence.",
      "Competence": 0,
      "Chunk": 59
    },
    {
      "Action": "Stands supportively beside Michelle at the coffin, engages in discussion about the money and novel.",
      "Warmth": 0,
      "Chunk": 60
    },
    {
      "Action": "Refuses to pay the money and tears up the check because the other person insulted his novel.",
      "Warmth": -1,
      "Chunk": 60
    },
    {
      "Action": "Explains that the money situation is complicated and refuses to pay when insulted about his novel, showing awareness and standing his ground.",
      "Competence": 1,
      "Chunk": 60
    },
    {
      "Action": "Tears up the check impulsively after the man talks bad about his novel, which may indicate a lack of emotional control or poor decision-making.",
      "Competence": -1,
      "Chunk": 60
    },
    {
      "Action": "Asks Norman why he is grinning nervously, showing concern.",
      "Warmth": 1,
      "Chunk": 61
    },
    {
      "Action": "Tells Michelle to check on their mother before leaving, showing responsibility and care.",
      "Warmth": 1,
      "Chunk": 61
    },
    {
      "Action": "Notices Norman's unusual behavior and sweat, correctly interprets that something serious has happened.",
      "Competence": 1,
      "Chunk": 61
    },
    {
      "Action": "Takes initiative to leave the room and instructs Michelle to check on their mother, showing responsibility and quick decision-making.",
      "Competence": 1,
      "Chunk": 61
    },
    {
      "Action": "Rushes over to the body in the study immediately upon entering, indicating attentiveness and urgency.",
      "Competence": 1,
      "Chunk": 61
    },
    {
      "Action": "Rushes over to the body and urgently calls for an ambulance.",
      "Warmth": 1,
      "Chunk": 62
    },
    {
      "Action": "Smacks Norman to help him calm down and tells him to pull himself together.",
      "Warmth": 1,
      "Chunk": 62
    },
    {
      "Action": "Expresses frustration about the situation and the difficulty of getting rid of the body.",
      "Warmth": 0,
      "Chunk": 62
    },
    {
      "Action": "Questions Jeff's suggestion to bury Uncle Edward with his father, showing concern and respect for the deceased.",
      "Warmth": 1,
      "Chunk": 63
    },
    {
      "Action": "Desperately tries to think of an alternative to Jeff's suggestion, indicating care and thoughtfulness.",
      "Warmth": 1,
      "Chunk": 63
    },
    {
      "Action": "Expresses skepticism about burying Uncle Edward with his father, indicating he is trying to think critically about the situation.",
      "Competence": 1,
      "Chunk": 63
    },
    {
      "Action": "Desperately tries to think of an alternative to the proposed plan but fails to come up with a solution.",
      "Competence": 0,
      "Chunk": 63
    },
    {
      "Action": "Slams bathroom door on Uncle Russell to keep him contained, shows frustration at Norman forgetting him on the toilet.",
      "Warmth": -1,
      "Chunk": 65
    },
    {
      "Action": "Runs to keep Derek from entering the room, tries to control the situation.",
      "Warmth": 0,
      "Chunk": 65
    },
    {
      "Action": "Opens the bathroom door to check on Uncle Russell and quickly slams it shut to hide him.",
      "Competence": 1,
      "Chunk": 65
    },
    {
      "Action": "Questions Norman sharply about forgetting Uncle Russell on the toilet, showing frustration but also awareness of the situation.",
      "Competence": 1,
      "Chunk": 65
    },
    {
      "Action": "Runs over to keep Derek from entering the study, attempting to control access and maintain secrecy.",
      "Competence": 1,
      "Chunk": 65
    },
    {
      "Action": "Opens the door only an inch and tries to deflect Derek's questions with vague answers.",
      "Competence": 0,
      "Chunk": 65
    },
    {
      "Action": "Fails to prevent Derek from realizing something is wrong, indicating limited control over the situation.",
      "Competence": -1,
      "Chunk": 65
    },
    {
      "Action": "Tells Ryan and Norman to wait and follows Jeff calmly instead of running, showing composure and responsibility.",
      "Warmth": 1,
      "Chunk": 66
    },
    {
      "Action": "Notices that everyone is captivated by Oscar's drama, indicating awareness but no direct intervention.",
      "Warmth": 0,
      "Chunk": 66
    },
    {
      "Action": "Realizes Elaine is following Oscar on the roof and uses the distraction to head back inside, avoiding involvement.",
      "Warmth": -1,
      "Chunk": 66
    },
    {
      "Action": "Tells Ryan and Norman to wait and follows Jeff calmly instead of running, showing measured behavior in a tense situation.",
      "Competence": 1,
      "Chunk": 66
    },
    {
      "Action": "Notices that everyone is captivated by the drama on the roof, indicating awareness of the social situation.",
      "Competence": 1,
      "Chunk": 66
    },
    {
      "Action": "Realizes Elaine climbing the roof is his chance and heads back inside, showing opportunistic thinking and situational awareness.",
      "Competence": 1,
      "Chunk": 66
    },
    {
      "Action": "Takes initiative to handle a difficult situation by organizing the removal of the body and coordinating with others.",
      "Warmth": 1,
      "Chunk": 67
    },
    {
      "Action": "Asks Michelle to stay out and prevent interruptions, showing trust in her ability to help.",
      "Warmth": 1,
      "Chunk": 67
    },
    {
      "Action": "Formulates a plan to get rid of a problematic person and delegates tasks to Michelle to prevent interruptions.",
      "Competence": 1,
      "Chunk": 67
    },
    {
      "Action": "Takes initiative by knocking on Norman's door and coordinating the moving of the body with Ryan and Norman.",
      "Competence": 1,
      "Chunk": 67
    },
    {
      "Action": "Shows respect and care by insisting they reposition their father's body properly in the coffin.",
      "Warmth": 1,
      "Chunk": 68
    },
    {
      "Action": "Responds seriously to Ryan's joking about their father, asking him to be serious.",
      "Warmth": 1,
      "Chunk": 68
    },
    {
      "Action": "Nods assent to Ryan's suggestion to proceed with putting their father in the coffin, showing cooperation.",
      "Warmth": 1,
      "Chunk": 68
    },
    {
      "Action": "Decides that the body position is wrong and insists on correcting it despite the awkwardness, showing awareness and responsibility.",
      "Competence": 1,
      "Chunk": 68
    },
    {
      "Action": "Nods assent to Ryan's suggestion to put their father in the coffin and helps lift the body, demonstrating cooperation and decisiveness.",
      "Competence": 1,
      "Chunk": 68
    },
    {
      "Action": "Shows seriousness and focus in a difficult emotional moment, contrasting with Ryan's laughter, indicating emotional maturity and situational awareness.",
      "Competence": 1,
      "Chunk": 68
    },
    {
      "Action": "Takes a moment to touch his father's hand and says goodbye before closing the coffin.",
      "Warmth": 1,
      "Chunk": 70
    },
    {
      "Action": "Silently assures others that the coffin is closed and the task is done, showing reliability and calmness.",
      "Warmth": 1,
      "Chunk": 70
    },
    {
      "Action": "Takes a moment to touch his father's hand before closing the coffin, showing emotional composure and respect.",
      "Competence": 1,
      "Chunk": 70
    },
    {
      "Action": "Quickly and silently closes the coffin with Ryan before Duncan enters, demonstrating timely and efficient action under pressure.",
      "Competence": 1,
      "Chunk": 70
    },
    {
      "Action": "Responds calmly and clearly to Michelle's question about whether Oscar is gone, providing reassurance.",
      "Competence": 1,
      "Chunk": 70
    },
    {
      "Action": "Remembers where he is and looks at Ryan, then rushes off to the study to find Uncle Russell.",
      "Competence": 1,
      "Chunk": 71
    },
    {
      "Action": "Apologizes sincerely to Uncle Russell for the confusion.",
      "Warmth": 1,
      "Chunk": 72
    },
    {
      "Action": "Feigns ignorance about the dead body to avoid conflict.",
      "Warmth": 0,
      "Chunk": 72
    },
    {
      "Action": "Expresses frustration about the day's events to Michelle.",
      "Warmth": 0,
      "Chunk": 72
    },
    {
      "Action": "Feigns ignorance about the dead body when confronted by Uncle Russell.",
      "Competence": -1,
      "Chunk": 72
    },
    {
      "Action": "Apologizes politely to Uncle Russell and attempts to explain the situation calmly.",
      "Competence": 1,
      "Chunk": 72
    },
    {
      "Action": "Moves to his seat without further addressing the confusion caused by Uncle Russell's claims.",
      "Competence": 0,
      "Chunk": 72
    },
    {
      "Action": "Promises Michelle about the condo and the baby, then hugs her to provide comfort.",
      "Warmth": 1,
      "Chunk": 73
    },
    {
      "Action": "Reassures Michelle that recent revelations do not change their relationship.",
      "Warmth": 1,
      "Chunk": 73
    },
    {
      "Action": "Promises Michelle to work things out despite the stressful situation, shows emotional support by hugging her.",
      "Competence": 1,
      "Chunk": 73
    },
    {
      "Action": "Acknowledges the difficulty of giving the eulogy after recent revelations but proceeds anyway.",
      "Competence": 1,
      "Chunk": 73
    },
    {
      "Action": "Responds promptly and cooperatively to Reverend Davis's request to proceed quickly with the funeral service.",
      "Competence": 1,
      "Chunk": 73
    },
    {
      "Action": "Decides firmly against an open casket despite the reverend's question, showing decisiveness.",
      "Competence": 1,
      "Chunk": 73
    },
    {
      "Action": "Prepares to deliver the eulogy calmly in a tense and silent room, indicating composure and readiness.",
      "Competence": 1,
      "Chunk": 73
    },
    {
      "Action": "Continues his eulogy nervously despite the disruptive banging and chaos.",
      "Warmth": 1,
      "Chunk": 74
    },
    {
      "Action": "Looks like a deer caught in headlights when the coffin bangs, but continues nervously with the eulogy despite the disruption.",
      "Competence": 0,
      "Chunk": 74
    },
    {
      "Action": "Bravely continues speaking in front of the crowd despite the shocking and chaotic interruptions.",
      "Competence": 1,
      "Chunk": 74
    },
    {
      "Action": "Shouts to restore order and honor his father, speaks sincerely about family love and respect, encourages focusing on important things despite flaws.",
      "Warmth": 1,
      "Chunk": 75
    },
    {
      "Action": "Shouts across the room to stop chaos and delivers a calm, heartfelt speech that commands attention and refocuses the mourners.",
      "Competence": 1,
      "Chunk": 75
    },
    {
      "Action": "Uses emotional intelligence to acknowledge flaws but emphasize positive qualities, showing insight and leadership.",
      "Competence": 1,
      "Chunk": 75
    },
    {
      "Action": "Manages to bring order and respect back to a chaotic situation through confident and skillful communication.",
      "Competence": 1,
      "Chunk": 75
    },
    {
      "Action": "Speaks warmly about his father as a decent, loving man who never condemned others and was free of prejudice.",
      "Warmth": 1,
      "Chunk": 76
    },
    {
      "Action": "Expresses hope to be half as good as his father, implying a desire to be generous and understanding.",
      "Warmth": 1,
      "Chunk": 76
    },
    {
      "Action": "Asks about his mother’s wellbeing, showing concern.",
      "Warmth": 1,
      "Chunk": 76
    },
    {
      "Action": "Delivers a heartfelt, composed eulogy that reflects understanding, respect, and emotional intelligence, earning the admiration of those present.",
      "Competence": 1,
      "Chunk": 76
    },
    {
      "Action": "Appears drained and vulnerable afterward, showing emotional exhaustion but also openness to support from family.",
      "Competence": 0,
      "Chunk": 76
    },
    {
      "Action": "Is surprised by Ryan's suggestion about their mother, indicating some lack of anticipation or preparation for family dynamics.",
      "Competence": 0,
      "Chunk": 76
    }
  ]
}