{
  "Silent Wolf": [
    {
      "Action": "Gives the Green Destiny Sword to Sir Te, acknowledging the deaths caused by it and choosing to part with it despite its significance.",
      "Warmth": 1,
      "Chunk": 2
    },
    {
      "Action": "Contemplates quitting and prays for forgiveness for not having avenged his master's death yet.",
      "Warmth": 1,
      "Chunk": 2
    },
    {
      "Action": "Is emotionally distant and does not respond when asked about his future plans.",
      "Warmth": 0,
      "Chunk": 2
    },
    {
      "Action": "Decides to give up the Green Destiny Sword, acknowledging the cost of the lives lost using it, showing deep reflection and a sense of responsibility.",
      "Competence": 1,
      "Chunk": 2
    },
    {
      "Action": "Breaks off meditation due to overwhelming sorrow and pull back from profound experience, indicating emotional struggle and hesitation.",
      "Competence": -1,
      "Chunk": 2
    },
    {
      "Action": "Plans to visit his master's grave for vengeance and forgiveness, showing determination and adherence to personal principles.",
      "Competence": 1,
      "Chunk": 2
    },
    {
      "Action": "Considers quitting despite his mission, revealing internal conflict and uncertainty about his path.",
      "Competence": -1,
      "Chunk": 2
    },
    {
      "Action": "Enters stealthily through a window, quickly retrieves and steals the sword, easily outwits Bo by leaping onto the roof and escapes.",
      "Competence": 1,
      "Chunk": 8
    },
    {
      "Action": "Expresses mistrust about a potentially deceptive poster, showing cautiousness and awareness of traps.",
      "Competence": 1,
      "Chunk": 15
    },
    {
      "Action": "Engages in questioning about the theft and its investigation, demonstrating diligence and proactivity.",
      "Competence": 1,
      "Chunk": 15
    },
    {
      "Action": "No direct action or indication of incompetence is present in the excerpt.",
      "Competence": 0,
      "Chunk": 15
    },
    {
      "Action": "Appears masked and intervenes at a critical moment, extending a sword to save Jade Fox who is about to be killed.",
      "Competence": 1,
      "Chunk": 16
    },
    {
      "Action": "Appears masked and saves Fox by extending sword at a critical moment, effectively intervening in combat.",
      "Competence": 1,
      "Chunk": 17
    },
    {
      "Action": "Answers Li's questions evasively and dismissively, showing some confidence but little willingness to reveal information.",
      "Competence": 0,
      "Chunk": 17
    },
    {
      "Action": "Does not answer directly who their master is and abruptly ends dialogue with 'Let's go!', avoiding deeper confrontation or explanation.",
      "Competence": 0,
      "Chunk": 17
    },
    {
      "Action": "Jen instinctively catches the tea pot with a lightning-fast move without looking down.",
      "Competence": 1,
      "Chunk": 19
    },
    {
      "Action": "Offers to teach and mentor a worthy disciple, encouraging calmness and growth.",
      "Warmth": 1,
      "Chunk": 20
    },
    {
      "Action": "Uses a stick to gently lift the figure's mask instead of aggression.",
      "Warmth": 1,
      "Chunk": 20
    },
    {
      "Action": "Uses agility and elusiveness skillfully to evade opponent's attacks and maintain control in a fight.",
      "Competence": 1,
      "Chunk": 20
    },
    {
      "Action": "Maintains composure while opponent loses theirs, demonstrating emotional control in combat.",
      "Competence": 1,
      "Chunk": 20
    },
    {
      "Action": "Attempts to teach and mentor, showing confidence in own skill and knowledge.",
      "Competence": 1,
      "Chunk": 20
    },
    {
      "Action": "Engages adversary without revealing own intentions fully, showing tactical awareness.",
      "Competence": 1,
      "Chunk": 20
    },
    {
      "Action": "Could imply some arrogance or dismissiveness by suggesting figure is not ready to hold the Green Destiny, but this is also part of tempering a student, so neutral.",
      "Competence": 0,
      "Chunk": 20
    },
    {
      "Action": "Covered for the girl to protect her and her father, avoiding embarrassment.",
      "Warmth": 1,
      "Chunk": 23
    },
    {
      "Action": "Expresses hope for the girl to receive proper training and avoid a destructive path.",
      "Warmth": 1,
      "Chunk": 23
    },
    {
      "Action": "Shows acceptance and patience by asking Shu Lien to be patient with him.",
      "Warmth": 1,
      "Chunk": 23
    },
    {
      "Action": "Orders the guards not to touch the women during the attack.",
      "Warmth": 1,
      "Chunk": 24
    },
    {
      "Action": "Seizes the comb from Jen's hand without concern for her feelings.",
      "Warmth": 0,
      "Chunk": 24
    },
    {
      "Action": "Not present or mentioned in the excerpt; no actions or behaviors to assess competence.",
      "Competence": 0,
      "Chunk": 24
    },
    {
      "Action": "Wraps Jen in animal fur for warmth, provides shelter and food despite her hostility.",
      "Warmth": 1,
      "Chunk": 25
    },
    {
      "Action": "Offers to make Jen a bow for hunting, shows consideration for her survival.",
      "Warmth": 1,
      "Chunk": 25
    },
    {
      "Action": "Insists Jen needs rest and food to regain strength, patiently guides her even when she attacks him.",
      "Warmth": 1,
      "Chunk": 25
    },
    {
      "Action": "Accepts Jen's aggression without retaliation, continuously tries to help her.",
      "Warmth": 1,
      "Chunk": 25
    },
    {
      "Action": "Quickly subdues multiple bandits, demonstrating effective combat skills and control of the situation.",
      "Competence": 1,
      "Chunk": 25
    },
    {
      "Action": "Manages to stop a fight and maintain order by calling out and asserting ownership over Jen.",
      "Competence": 1,
      "Chunk": 25
    },
    {
      "Action": "Recognizes the need for rest and water, suggesting taking a break and identifying a creek, showing survival awareness.",
      "Competence": 1,
      "Chunk": 25
    },
    {
      "Action": "Provides shelter, food, and supplies, including making a bow and arrows, indicating resourcefulness and care.",
      "Competence": 1,
      "Chunk": 25
    },
    {
      "Action": "Patiently aids Jen despite her initial aggression, showing emotional intelligence and practical wisdom.",
      "Competence": 1,
      "Chunk": 25
    },
    {
      "Action": "Sharpening his arrows carefully in preparation for potential danger.",
      "Competence": 1,
      "Chunk": 26
    },
    {
      "Action": "Brings fresh water to a remote cave despite difficulties, showing resourcefulness.",
      "Competence": 1,
      "Chunk": 26
    },
    {
      "Action": "Unties Jen and allows her access to clean clothes and a bath, indicating a strategic and composed approach to captivity.",
      "Competence": 1,
      "Chunk": 26
    },
    {
      "Action": "Sings to let Jen know where he is, suggesting calculated communication to maintain control and avoid surprises.",
      "Competence": 1,
      "Chunk": 26
    },
    {
      "Action": "Sings a loud rendition of a tribal song and La-las through passages, which brings a smile to Jen.",
      "Warmth": 1,
      "Chunk": 27
    },
    {
      "Action": "Pulls cactus needles from Jen’s feet to help her despite the pain involved.",
      "Warmth": 1,
      "Chunk": 27
    },
    {
      "Action": "Mocks Jen by saying he uses her comb to pick fleas from his horse, showing playful teasing.",
      "Warmth": 1,
      "Chunk": 27
    },
    {
      "Action": "Refuses to return the comb on command and asserts he doesn't take orders from anyone.",
      "Warmth": -1,
      "Chunk": 27
    },
    {
      "Action": "Engages in a physical tussle with Jen after being stabbed, which leads into consensual passionate intimacy.",
      "Warmth": 0,
      "Chunk": 27
    },
    {
      "Action": "Sings loudly and confidently, even if imperfectly recalling lyrics, indicating comfort and presence.",
      "Competence": 1,
      "Chunk": 27
    },
    {
      "Action": "Pulls cactus needles from Jen's feet carefully, showing attentiveness and skill.",
      "Competence": 1,
      "Chunk": 27
    },
    {
      "Action": "Refuses to return Jen's comb and resists taking orders, showing confidence and assertiveness.",
      "Competence": 1,
      "Chunk": 27
    },
    {
      "Action": "Lunges at Jen fiercely after being stabbed, demonstrating physical capability and boldness.",
      "Competence": 1,
      "Chunk": 27
    },
    {
      "Action": "Briefly loses control as tussle turns to passion, showing impulsivity but also emotional depth.",
      "Competence": 0,
      "Chunk": 27
    },
    {
      "Action": "Reveals background and motivation clearly and honestly, demonstrating self-awareness.",
      "Competence": 1,
      "Chunk": 27
    },
    {
      "Action": "Explains that a gang becomes a family and shares personal insight on survival.",
      "Warmth": 1,
      "Chunk": 28
    },
    {
      "Action": "Expresses desire for a lasting relationship and to earn respect, showing commitment and sincerity.",
      "Warmth": 1,
      "Chunk": 28
    },
    {
      "Action": "Warns Jen about danger from her father's men, showing concern for her safety.",
      "Warmth": 1,
      "Chunk": 28
    },
    {
      "Action": "Observes enemy movements through binoculars, assesses ongoing threat.",
      "Competence": 1,
      "Chunk": 28
    },
    {
      "Action": "Acknowledges danger realistically and communicates it clearly to Jen.",
      "Competence": 1,
      "Chunk": 28
    },
    {
      "Action": "Expresses emotional desires and hopes (e.g., wanting Jen to be his forever and promising to make a mark), showing confidence in future plans.",
      "Competence": 1,
      "Chunk": 28
    },
    {
      "Action": "Does not take immediate action to evade or confront the enemy’s pursuit, instead engages in dialogue and reflection.",
      "Competence": 0,
      "Chunk": 28
    },
    {
      "Action": "Gives Jen a precious jade comb as a token to keep safe, promising to return it and showing care during their intimate moment.",
      "Warmth": 1,
      "Chunk": 29
    },
    {
      "Action": "Tries to stop Jen's marriage, expressing fear of losing her and a desire to protect her choices.",
      "Warmth": 1,
      "Chunk": 29
    },
    {
      "Action": "Leaves quietly after a tense farewell, respecting Jen's wishes despite his own feelings.",
      "Warmth": 1,
      "Chunk": 29
    },
    {
      "Action": "No direct action or statement by Silent Wolf present in the excerpt.",
      "Competence": 0,
      "Chunk": 33
    },
    {
      "Action": "No explicit actions or statements in this excerpt to evaluate warmth.",
      "Warmth": 0,
      "Chunk": 35
    },
    {
      "Action": "Leaps off the bamboo tree and throws Jen toward the ground, maintaining strong control in combat.",
      "Competence": 1,
      "Chunk": 38
    },
    {
      "Action": "Successfully takes back the sword in three moves during a challenge with Jen.",
      "Competence": 1,
      "Chunk": 38
    },
    {
      "Action": "Throws the sword into the rapids to deny Jen its use, showing decisiveness.",
      "Competence": 1,
      "Chunk": 38
    },
    {
      "Action": "Chases Jen downstream by hopping on rocks, showing agility and persistence.",
      "Competence": 1,
      "Chunk": 38
    },
    {
      "Action": "Fails to catch Jen and Jade Fox after losing them in the rapids.",
      "Competence": -1,
      "Chunk": 38
    },
    {
      "Action": "Li carries Jen inside to help her after she was drugged and tends to her condition attentively.",
      "Warmth": 1,
      "Chunk": 39
    },
    {
      "Action": "Li fights Jade Fox to protect Jen and others from her attack.",
      "Warmth": 1,
      "Chunk": 39
    },
    {
      "Action": "The excerpt does not show any actions, statements, or presence of Silent Wolf.",
      "Competence": 0,
      "Chunk": 39
    }
  ],
  "Silent Wolf ": [
    {
      "Action": "Successfully covered for the girl to recover the sword without embarrassing anyone, showing strategic thinking and discretion.",
      "Competence": 1,
      "Chunk": 23
    },
    {
      "Action": "Expresses willingness to patiently handle a difficult situation and acknowledges ongoing cycles of violence, indicating self-awareness and emotional intelligence.",
      "Competence": 1,
      "Chunk": 23
    },
    {
      "Action": "Contemplates unconventional solutions (suggesting making an exception to accept a female disciple at Wudan) to address complex problems, showing adaptability and leadership.",
      "Competence": 1,
      "Chunk": 23
    }
  ]
}